caterva/__init__.py
caterva/caterva_ext.cp310-win_amd64.pyd
caterva/constructors.py
caterva/info.py
caterva/meta.py
caterva/ndarray.py
caterva/utils.py
caterva/version.py
caterva-0.7.3.data/data/include/caterva.h
caterva-0.7.3.data/data/lib/caterva.dll
caterva-0.7.3.data/data/lib/libcaterva.lib
caterva-0.7.3.dist-info/LICENSE
caterva-0.7.3.dist-info/METADATA
caterva-0.7.3.dist-info/WHEEL
caterva-0.7.3.dist-info/top_level.txt
caterva-0.7.3.dist-info/RECORD
