Metadata-Version: 2.1
Name: caterva
Version: 0.7.3
Summary: Caterva for Python (multidimensional compressed data containers).
Home-page: https://github.com/Blosc/python-caterva
Author: Blosc Development Team
Author-email: blosc@blosc.org
Maintainer: Blosc Development Team
Maintainer-email: blosc@blosc.org
License: https://opensource.org/licenses/BSD-3-Clause
Platform: any
Classifier: Development Status :: 3 - Alpha
Classifier: Intended Audience :: Developers
Classifier: Intended Audience :: Information Technology
Classifier: Intended Audience :: Science/Research
Classifier: License :: OSI Approved :: BSD License
Classifier: Programming Language :: Python
Classifier: Topic :: Software Development :: Libraries :: Python Modules
Classifier: Operating System :: Microsoft :: Windows
Classifier: Operating System :: Unix
Classifier: Programming Language :: Python :: 3
Classifier: Programming Language :: Python :: 3.6
Classifier: Programming Language :: Python :: 3.7
Classifier: Programming Language :: Python :: 3.8
License-File: LICENSE
Requires-Dist: ndindex
Requires-Dist: msgpack
